Metadata-Version: 2.1
Name: test_package_smirnova_ea
Version: 0.0.1
Summary: My Package
